src/Pbmm2Workflow.py
src/commands.py
src/config_utils.py
src/constants.py
src/env_utils.py
src/file_utils.py
src/logging_utils.py
src/preprocess_files.py
src/qc_utils.py
src/run_pbmm2.py
src/run_qc.py
o2_processing_utils-0.1.3.dist-info/LICENSE
o2_processing_utils-0.1.3.dist-info/METADATA
o2_processing_utils-0.1.3.dist-info/WHEEL
o2_processing_utils-0.1.3.dist-info/entry_points.txt
o2_processing_utils-0.1.3.dist-info/RECORD
