Metadata-Version: 2.1
Name: o2-processing-utils
Version: 0.1.3
Summary: Runs a variety of bioinformatics tools on O2 (HMS' HPC), such as long read alignment and QC
Home-page: https://github.com/smaht-dac/o2-processing-utils
License: MIT
Author: William Feng
Author-email: william_feng@hms.harvard.edu
Requires-Python: >=3.8,<3.12
Classifier: License :: OSI Approved :: MIT License
Classifier: Natural Language :: English
Classifier: Operating System :: POSIX :: Linux
Classifier: Programming Language :: Python :: 3
Classifier: Programming Language :: Python :: 3.8
Classifier: Programming Language :: Python :: 3.9
Classifier: Programming Language :: Python :: 3.10
Classifier: Programming Language :: Python :: 3.11
Requires-Dist: click (>=8.1.3,<9.0.0)
Requires-Dist: pydantic (>=2.5.0,<3.0.0)
Requires-Dist: rich (>=13.7.0,<14.0.0)
Project-URL: Repository, https://github.com/smaht-dac/o2-processing-utils
